Workbook
Name Slicer_Category: #N/A
Name Slicer_Region: #N/A
Name Slicer_Segment: #N/A

Sheet Dashboard
B10: Subcategory | C10: 2017 | D10: 2018 | E10: Growth | H10: State | I10: 2017 | J10: 2018 | K10: Growth | N10: City | O10: 2017 | P10: 2018 | Q10: Growth
B11: =Sheet4!G32 -> Accessories | C11: =Sheet4!H32 -> 41735.364 | D11: =Sheet4!I32 -> 58240.97 | E11: =D11/C11-1 -> 0.3954825 | H11: =Sheet4!K32 -> California | I11: =Sheet4!L32 -> 126542.96 | J11: =Sheet4!M32 -> 144666.77 | K11: =J11/I11-1 -> 0.14322254 | N11: =Sheet4!O32 -> Chicago | O11: =Sheet4!P32 -> 13067.55 | P11: =Sheet4!Q32 -> 15742.043 | Q11: =P11/O11-1 -> 0.20466675
B12: =Sheet4!G33 -> Appliances | C12: =Sheet4!H33 -> 26016.787 | D12: =Sheet4!I33 -> 40212.722 | E12: =D12/C12-1 -> 0.5456452 | H12: =Sheet4!K33 -> Florida | I12: =Sheet4!L33 -> 13528.963 | J12: =Sheet4!M33 -> 26444.715 | K12: =J12/I12-1 -> 0.95467417 | N12: =Sheet4!O33 -> Columbus | O12: =Sheet4!P33 -> 9506.412 | P12: =Sheet4!Q33 -> 17571.473 | Q12: =P12/O12-1 -> 0.84838118
B13: =Sheet4!G34 -> Binders | C13: =Sheet4!H34 -> 48994.517 | D13: =Sheet4!I34 -> 71721.255 | E13: =D13/C13-1 -> 0.46386288 | H13: =Sheet4!K34 -> Illinois | I13: =Sheet4!L34 -> 21033.719 | J13: =Sheet4!M34 -> 23848.043 | K13: =J13/I13-1 -> 0.13380059 | N13: =Sheet4!O34 -> Detroit | O13: =Sheet4!P34 -> 21197.32 | P13: =Sheet4!Q34 -> 12148.886 | Q13: =P13/O13-1 -> -0.42686689
B14: =Sheet4!G35 -> Bookcases | C14: =Sheet4!H35 -> 26275.466 | D14: =Sheet4!I35 -> 30024.28 | E14: =D14/C14-1 -> 0.14267352 | H14: =Sheet4!K35 -> Indiana | I14: =Sheet4!L35 -> 25461.78 | J14: =Sheet4!M35 -> 13685.43 | K14: =J14/I14-1 -> -0.46251087 | N14: =Sheet4!O35 -> Houston | O14: =Sheet4!P35 -> 16349.113 | P14: =Sheet4!Q35 -> 16212.806 | Q14: =P14/O14-1 -> -0.0083372717
B15: =Sheet4!G36 -> Chairs | C15: =Sheet4!H36 -> 81930.345 | D15: =Sheet4!I36 -> 93191.273 | E15: =D15/C15-1 -> 0.13744514 | H15: =Sheet4!K36 -> Michigan | I15: =Sheet4!L36 -> 27286.495 | J15: =Sheet4!M36 -> 25833.649 | K15: =J15/I15-1 -> -0.053244141 | N15: =Sheet4!O36 -> Lafayette | O15: =Sheet4!P36 -> 18431.34 | P15: =Sheet4!Q36 -> 5630.51 | Q15: =P15/O15-1 -> -0.69451434
B16: =Sheet4!G37 -> Copiers | C16: =Sheet4!H37 -> 46319.474 | D16: =Sheet4!I37 -> 62899.388 | E16: =D16/C16-1 -> 0.35794694 | H16: =Sheet4!K37 -> New York | I16: =Sheet4!L37 -> 70826.558 | J16: =Sheet4!M37 -> 93772.167 | K16: =J16/I16-1 -> 0.323969 | N16: =Sheet4!O37 -> Los Angeles | O16: =Sheet4!P37 -> 55273.118 | P16: =Sheet4!Q37 -> 48173.172 | Q16: =P16/O16-1 -> -0.12845205
B17: =Sheet4!G38 -> Machines | C17: =Sheet4!H38 -> 55906.886 | D17: =Sheet4!I38 -> 43544.675 | E17: =D17/C17-1 -> -0.22112144 | H17: =Sheet4!K38 -> Ohio | I17: =Sheet4!L38 -> 24135.082 | J17: =Sheet4!M38 -> 21372.76 | K17: =J17/I17-1 -> -0.11445256 | N17: =Sheet4!O38 -> New York City | O17: =Sheet4!P38 -> 53806.554 | P17: =Sheet4!Q38 -> 86788.773 | Q17: =P17/O17-1 -> 0.61297772
B18: =Sheet4!G39 -> Phones | C18: =Sheet4!H39 -> 78000.22 | D18: =Sheet4!I39 -> 104685.66 | E18: =D18/C18-1 -> 0.34212004 | H18: =Sheet4!K39 -> Pennsylvania | I18: =Sheet4!L39 -> 32996.372 | J18: =Sheet4!M39 -> 42688.306 | K18: =J18/I18-1 -> 0.29372726 | N18: =Sheet4!O39 -> Philadelphia | O18: =Sheet4!P39 -> 30234.666 | P18: =Sheet4!Q39 -> 41595.502 | Q18: =P18/O18-1 -> 0.3757553
B19: =Sheet4!G40 -> Storage | C19: =Sheet4!H40 -> 58751.956 | D19: =Sheet4!I40 -> 68072.702 | E19: =D19/C19-1 -> 0.15864571 | H19: =Sheet4!K40 -> Texas | I19: =Sheet4!L40 -> 41005.376 | J19: =Sheet4!M40 -> 43421.758 | K19: =J19/I19-1 -> 0.058928424 | N19: =Sheet4!O40 -> San Francisco | O19: =Sheet4!P40 -> 27021.641 | P19: =Sheet4!Q40 -> 36899.091 | Q19: =P19/O19-1 -> 0.3655385
B20: =Sheet4!G41 -> Tables | C20: =Sheet4!H41 -> 60762.112 | D20: =Sheet4!I41 -> 60893.543 | E20: =D20/C20-1 -> 0.0021630255 | H20: =Sheet4!K41 -> Washington | I20: =Sheet4!L41 -> 19814.284 | J20: =Sheet4!M41 -> 65539.896 | K20: =J20/I20-1 -> 2.3077095 | N20: =Sheet4!O41 -> Seattle | O20: =Sheet4!P41 -> 16158.722 | P20: =Sheet4!Q41 -> 56990.82 | Q20: =P20/O20-1 -> 2.5269386
B21: =Sheet4!G42 -> Grand Total | C21: =Sheet4!H42 -> 524693.13 | D21: =Sheet4!I42 -> 633486.47 | E21: =D21/C21-1 -> 0.2073466 | H21: =Sheet4!K42 -> Grand Total | I21: =Sheet4!L42 -> 402631.59 | J21: =Sheet4!M42 -> 501273.49 | K21: =J21/I21-1 -> 0.24499295 | N21: =Sheet4!O42 -> Grand Total | O21: =Sheet4!P42 -> 261046.44 | P21: =Sheet4!Q42 -> 337753.08 | Q21: =P21/O21-1 -> 0.29384289

Sheet Sheet4
A3: Sum of Sales | B3: Column Labels | L3: Sum of Sales | M3: Column Labels
A4: Row Labels | B4: Technology | C4: Furniture | D4: Office Supplies | E4: Grand Total | L4: Row Labels | M4: South | N4: Grand Total
A5: 2015 | B5: 173865.51 | C5: 156477.88 | D5: 149512.82 | E5: 479856.21 | L5: 2015 | M5: 103374.91 | N5: 103374.91
A6: 2016 | B6: 162257.73 | C6: 164053.87 | D6: 133124.41 | E6: 459436.01 | L6: Qtr1 | M6: 44236.951 | N6: 44236.951
A7: 2017 | B7: 221961.94 | C7: 195813.04 | D7: 182417.57 | E7: 600192.55 | L7: Qtr2 | M7: 22408.743 | N7: 22408.743
A8: 2018 | B8: 269370.69 | C8: 212313.79 | D8: 240367.54 | E8: 722052.02 | L8: Qtr3 | M8: 15774.412 | N8: 15774.412
A9: Grand Total | B9: 827455.87 | C9: 728658.58 | D9: 705422.33 | E9: 2261536.8 | L9: Qtr4 | M9: 20954.8 | N9: 20954.8
L10: 2016 | M10: 70076.082 | N10: 70076.082
L11: Qtr1 | M11: 16444.443 | N11: 16444.443
L12: Qtr2 | M12: 15056.286 | N12: 15056.286
L13: Qtr3 | M13: 21373.525 | N13: 21373.525
L14: Qtr4 | M14: 17201.828 | N14: 17201.828
L15: 2017 | M15: 93535.903 | N15: 93535.903
L16: Qtr1 | M16: 23933.704 | N16: 23933.704
L17: Qtr2 | M17: 18381.828 | N17: 18381.828
L18: Qtr3 | M18: 21635.881 | N18: 21635.881
L19: Qtr4 | M19: 29584.491 | N19: 29584.491
L20: 2018 | M20: 122164.57 | N20: 122164.57
L21: Qtr1 | M21: 13642.182 | N21: 13642.182
... L23: Qtr3 | M23: 23418.952 | N23: 23418.952
A24: Row Labels | B24: Sum of Sales | L24: Qtr4 | M24: 55778.019 | N24: 55778.019
A25: 2017 | B25: 600192.55 | D25: =GETPIVOTDATA("Sales",$A$24,"Years (Order Date)",2018)/GETPIVOTDATA("Sales",$A$24,"Years (Order Date)",2017)-1 -> 0.20303396 | L25: Grand Total | M25: 389151.46 | N25: 389151.46
A26: 2018 | B26: 722052.02 | D26: =GETPIVOTDATA("Sales",$A$24,"Years (Order Date)",2017) -> 600192.55
A27: Grand Total | B27: 1322244.6 | D27: =GETPIVOTDATA("Sales",$A$24,"Years (Order Date)",2018) -> 722052.02
A30: Row Labels | B30: Sum of Sales | G30: Sum of Sales | H30: Column Labels | K30: Sum of Sales | L30: Column Labels | O30: Sum of Sales | P30: Column Labels
A31: California | B31: 446306.46 | G31: Row Labels | H31: 2017 | I31: 2018 | K31: Row Labels | L31: 2017 | M31: 2018 | O31: Row Labels | P31: 2017 | Q31: 2018
A32: Grand Total | B32: 446306.46 | G32: Accessories | H32: 41735.364 | I32: 58240.97 | K32: California | L32: 126542.96 | M32: 144666.77 | O32: Chicago | P32: 13067.55 | Q32: 15742.043
G33: Appliances | H33: 26016.787 | I33: 40212.722 | K33: Florida | L33: 13528.963 | M33: 26444.715 | O33: Columbus | P33: 9506.412 | Q33: 17571.473
G34: Binders | H34: 48994.517 | I34: 71721.255 | K34: Illinois | L34: 21033.719 | M34: 23848.043 | O34: Detroit | P34: 21197.32 | Q34: 12148.886
A35: Row Labels | B35: Sum of Sales | G35: Bookcases | H35: 26275.466 | I35: 30024.28 | K35: Indiana | L35: 25461.78 | M35: 13685.43 | O35: Houston | P35: 16349.113 | Q35: 16212.806
A36: Phones | B36: 327782.45 | G36: Chairs | H36: 81930.345 | I36: 93191.273 | K36: Michigan | L36: 27286.495 | M36: 25833.649 | O36: Lafayette | P36: 18431.34 | Q36: 5630.51
A37: Grand Total | B37: 327782.45 | G37: Copiers | H37: 46319.474 | I37: 62899.388 | K37: New York | L37: 70826.558 | M37: 93772.167 | O37: Los Angeles | P37: 55273.118 | Q37: 48173.172
G38: Machines | H38: 55906.886 | I38: 43544.675 | K38: Ohio | L38: 24135.082 | M38: 21372.76 | O38: New York City | P38: 53806.554 | Q38: 86788.773
G39: Phones | H39: 78000.22 | I39: 104685.66 | K39: Pennsylvania | L39: 32996.372 | M39: 42688.306 | O39: Philadelphia | P39: 30234.666 | Q39: 41595.502
G40: Storage | H40: 58751.956 | I40: 68072.702 | K40: Texas | L40: 41005.376 | M40: 43421.758 | O40: San Francisco | P40: 27021.641 | Q40: 36899.091
A41: Row Labels | B41: Average of Sales | D41: State | E41: Sales | G41: Tables | H41: 60762.112 | I41: 60893.543 | K41: Washington | L41: 19814.284 | M41: 65539.896 | O41: Seattle | P41: 16158.722 | Q41: 56990.82
A42: Alabama | B42: 319.84656 | D42: =A42 -> Alabama | E42: =B42 -> 319.84656 | G42: Grand Total | H42: 524693.13 | I42: 633486.47 | K42: Grand Total | L42: 402631.59 | M42: 501273.49 | O42: Grand Total | P42: 261046.44 | Q42: 337753.08
A43: Arizona | B43: 158.17335 | D43: =A43 -> Arizona | E43: =B43 -> 158.17335
A44: Arkansas | B44: 194.6355 | D44: =A44 -> Arkansas | E44: =B44 -> 194.6355
A45: California | B45: 229.34556 | D45: =A45 -> California | E45: =B45 -> 229.34556
A46: Colorado | B46: 177.88602 | D46: =A46 -> Colorado | E46: =B46 -> 177.88602
A47: Connecticut | B47: 163.22387 | D47: =A47 -> Connecticut | E47: =B47 -> 163.22387
A48: Delaware | B48: 293.79569 | D48: =A48 -> Delaware | E48: =B48 -> 293.79569
A49: District of Columbia | B49: 286.502 | D49: =A49 -> District of Columbia | E49: =B49 -> 286.502
A50: Florida | B50: 237.09526 | D50: =A50 -> Florida | E50: =B50 -> 237.09526
A51: Georgia | B51: 272.42435 | D51: =A51 -> Georgia | E51: =B51 -> 272.42435
A52: Idaho | B52: 208.68981 | D52: =A52 -> Idaho | E52: =B52 -> 208.68981
A53: Illinois | B53: 164.05076 | D53: =A53 -> Illinois | E53: =B53 -> 164.05076
A54: Indiana | B54: 360.87704 | D54: =A54 -> Indiana | E54: =B54 -> 360.87704
... A90: Wyoming | B90: 1603.136 | D90: =A90 -> Wyoming | E90: =B90 -> 1603.136

Sheet train (2)
A1: Row ID | B1: Order ID | C1: Order Date | D1: Ship Date | E1: Ship Mode | F1: Customer ID | G1: Customer Name | H1: Segment | I1: Country | J1: City | K1: State | L1: Postal Code | M1: Region | N1: Product ID | O1: Category | P1: Sub-Category | Q1: Product Name | R1: Sales
A2: 1 | B2: CA-2017-152156 | C2: 43047 | D2: 43050 | E2: Second Class | F2: CG-12520 | G2: Claire Gute | H2: Consumer | I2: United States | J2: Henderson | K2: Kentucky | L2: 42420 | M2: South | N2: FUR-BO-10001798 | O2: Furniture | P2: Bookcases | Q2: Bush Somerset Collection Bookcase | R2: 261.96
A3: 2 | B3: CA-2017-152156 | C3: 43047 | D3: 43050 | E3: Second Class | F3: CG-12520 | G3: Claire Gute | H3: Consumer | I3: United States | J3: Henderson | K3: Kentucky | L3: 42420 | M3: South | N3: FUR-CH-10000454 | O3: Furniture | P3: Chairs | Q3: Hon Deluxe Fabric Upholstered Stacking Chairs, Rounded Back | R3: 731.94
A4: 3 | B4: CA-2017-138688 | C4: 42898 | D4: 42902 | E4: Second Class | F4: DV-13045 | G4: Darrin Van Huff | H4: Corporate | I4: United States | J4: Los Angeles | K4: California | L4: 90036 | M4: West | N4: OFF-LA-10000240 | O4: Office Supplies | P4: Labels | Q4: Self-Adhesive Address Labels for Typewriters by Universal | R4: 14.62
A5: 4 | B5: US-2016-108966 | C5: 42654 | D5: 42661 | E5: Standard Class | F5: SO-20335 | G5: Sean O'Donnell | H5: Consumer | I5: United States | J5: Fort Lauderdale | K5: Florida | L5: 33311 | M5: South | N5: FUR-TA-10000577 | O5: Furniture | P5: Tables | Q5: Bretford CR4500 Series Slim Rectangular Table | R5: 957.5775
A6: 5 | B6: US-2016-108966 | C6: 42654 | D6: 42661 | E6: Standard Class | F6: SO-20335 | G6: Sean O'Donnell | H6: Consumer | I6: United States | J6: Fort Lauderdale | K6: Florida | L6: 33311 | M6: South | N6: OFF-ST-10000760 | O6: Office Supplies | P6: Storage | Q6: Eldon Fold 'N Roll Cart System | R6: 22.368
A7: 6 | B7: CA-2015-115812 | C7: 42164 | D7: 42169 | E7: Standard Class | F7: BH-11710 | G7: Brosina Hoffman | H7: Consumer | I7: United States | J7: Los Angeles | K7: California | L7: 90032 | M7: West | N7: FUR-FU-10001487 | O7: Furniture | P7: Furnishings | Q7: Eldon Expressions Wood and Plastic Desk Accessories, Cherry Wood | R7: 48.86
A8: 7 | B8: CA-2015-115812 | C8: 42164 | D8: 42169 | E8: Standard Class | F8: BH-11710 | G8: Brosina Hoffman | H8: Consumer | I8: United States | J8: Los Angeles | K8: California | L8: 90032 | M8: West | N8: OFF-AR-10002833 | O8: Office Supplies | P8: Art | Q8: Newell 322 | R8: 7.28
A9: 8 | B9: CA-2015-115812 | C9: 42164 | D9: 42169 | E9: Standard Class | F9: BH-11710 | G9: Brosina Hoffman | H9: Consumer | I9: United States | J9: Los Angeles | K9: California | L9: 90032 | M9: West | N9: TEC-PH-10002275 | O9: Technology | P9: Phones | Q9: Mitel 5320 IP Phone VoIP phone | R9: 907.152
A10: 9 | B10: CA-2015-115812 | C10: 42164 | D10: 42169 | E10: Standard Class | F10: BH-11710 | G10: Brosina Hoffman | H10: Consumer | I10: United States | J10: Los Angeles | K10: California | L10: 90032 | M10: West | N10: OFF-BI-10003910 | O10: Office Supplies | P10: Binders | Q10: DXL Angle-View Binders with Locking Rings by Samsill | R10: 18.504
A11: 10 | B11: CA-2015-115812 | C11: 42164 | D11: 42169 | E11: Standard Class | F11: BH-11710 | G11: Brosina Hoffman | H11: Consumer | I11: United States | J11: Los Angeles | K11: California | L11: 90032 | M11: West | N11: OFF-AP-10002892 | O11: Office Supplies | P11: Appliances | Q11: Belkin F5C206VTEL 6 Outlet Surge | R11: 114.9
A12: 11 | B12: CA-2015-115812 | C12: 42164 | D12: 42169 | E12: Standard Class | F12: BH-11710 | G12: Brosina Hoffman | H12: Consumer | I12: United States | J12: Los Angeles | K12: California | L12: 90032 | M12: West | N12: FUR-TA-10001539 | O12: Furniture | P12: Tables | Q12: Chromcraft Rectangular Conference Tables | R12: 1706.184
A13: 12 | B13: CA-2015-115812 | C13: 42164 | D13: 42169 | E13: Standard Class | F13: BH-11710 | G13: Brosina Hoffman | H13: Consumer | I13: United States | J13: Los Angeles | K13: California | L13: 90032 | M13: West | N13: TEC-PH-10002033 | O13: Technology | P13: Phones | Q13: Konftel 250 Conference phone - Charcoal black | R13: 911.424
... A2235: 2234 | B2235: CA-2016-123232 | C2235: 42718 | D2235: 42720 | E2235: Second Class | F2235: DJ-13630 | G2235: Doug Jacobs | H2235: Consumer | I2235: United States | J2235: Portland | K2235: Oregon | L2235: 97206 | M2235: West | N2235: TEC-PH-10001051 | O2235: Technology | P2235: Phones | Q2235: HTC One | R2235: 319.968
A2236: 2235 | B2236: CA-2018-104066 | C2236: 43439 | D2236: 43444 | E2236: Standard Class | F2236: QJ-19255 | G2236: Quincy Jones | H2236: Corporate | I2236: United States | J2236: Burlington | K2236: Vermont | M2236: East | N2236: TEC-AC-10001013 | O2236: Technology | P2236: Accessories | Q2236: Logitech ClearChat Comfort/USB Headset H390 | R2236: 205.03
A2237: 2236 | B2237: CA-2016-145849 | C2237: 42628 | D2237: 42630 | E2237: Second Class | F2237: CT-11995 | G2237: Carol Triggs | H2237: Consumer | I2237: United States | J2237: Indianapolis | K2237: Indiana | L2237: 46203 | M2237: Central | N2237: OFF-ST-10000025 | O2237: Office Supplies | P2237: Storage | Q2237: Fellowes Stor/Drawer Steel Plus Storage Drawers | R2237: 190.86
A2238: 2237 | B2238: CA-2016-145849 | C2238: 42628 | D2238: 42630 | E2238: Second Class | F2238: CT-11995 | G2238: Carol Triggs | H2238: Consumer | I2238: United States | J2238: Indianapolis | K2238: Indiana | L2238: 46203 | M2238: Central | N2238: OFF-AR-10000817 | O2238: Office Supplies | P2238: Art | Q2238: Manco Dry-Lighter Erasable Highlighter | R2238: 24.32
A2239: 2238 | B2239: CA-2017-122322 | C2239: 42931 | D2239: 42937 | E2239: Standard Class | F2239: RH-19510 | G2239: Rick Huthwaite | H2239: Home Office | I2239: United States | J2239: Provo | K2239: Utah | L2239: 84604 | M2239: West | N2239: OFF-SU-10000952 | O2239: Office Supplies | P2239: Supplies | Q2239: Fiskars Home & Office Scissors | R2239: 44.4
A2240: 2239 | B2240: CA-2018-166849 | C2240: 43210 | D2240: 43216 | E2240: Standard Class | F2240: SJ-20125 | G2240: Sanjit Jacobs | H2240: Home Office | I2240: United States | J2240: Chicago | K2240: Illinois | L2240: 60610 | M2240: Central | N2240: FUR-FU-10004597 | O2240: Furniture | P2240: Furnishings | Q2240: Eldon Cleatmat Chair Mats for Medium Pile Carpets | R2240: 44.4
A2241: 2240 | B2241: CA-2017-146633 | C2241: 43054 | D2241: 43056 | E2241: Second Class | F2241: TG-21310 | G2241: Toby Gnade | H2241: Consumer | I2241: United States | J2241: Los Angeles | K2241: California | L2241: 90049 | M2241: West | N2241: OFF-BI-10003527 | O2241: Office Supplies | P2241: Binders | Q2241: Fellowes PB500 Electric Punch Plastic Comb Binding Machine with Manual Bind | R2241: 1016.792
A2242: 2241 | B2242: CA-2017-146633 | C2242: 43054 | D2242: 43056 | E2242: Second Class | F2242: TG-21310 | G2242: Toby Gnade | H2242: Consumer | I2242: United States | J2242: Los Angeles | K2242: California | L2242: 90049 | M2242: West | N2242: OFF-BI-10002982 | O2242: Office Supplies | P2242: Binders | Q2242: Avery Self-Adhesive Photo Pockets for Polaroid Photos | R2242: 38.136
A2243: 2242 | B2243: US-2017-126893 | C2243: 43065 | D2243: 43070 | E2243: Standard Class | F2243: CT-11995 | G2243: Carol Triggs | H2243: Consumer | I2243: United States | J2243: Philadelphia | K2243: Pennsylvania | L2243: 19134 | M2243: East | N2243: TEC-PH-10004165 | O2243: Technology | P2243: Phones | Q2243: Mitel MiVoice 5330e IP Phone | R2243: 494.982
A2244: 2243 | B2244: CA-2018-103380 | C2244: 43425 | D2244: 43429 | E2244: Standard Class | F2244: BF-11005 | G2244: Barry Franz | H2244: Home Office | I2244: United States | J2244: Pasadena | K2244: California | L2244: 91104 | M2244: West | N2244: OFF-ST-10003442 | O2244: Office Supplies | P2244: Storage | Q2244: Eldon Portable Mobile Manager | R2244: 56.56
A2245: 2244 | B2245: CA-2018-103380 | C2245: 43425 | D2245: 43429 | E2245: Standard Class | F2245: BF-11005 | G2245: Barry Franz | H2245: Home Office | I2245: United States | J2245: Pasadena | K2245: California | L2245: 91104 | M2245: West | N2245: OFF-AR-10003856 | O2245: Office Supplies | P2245: Art | Q2245: Newell 344 | R2245: 5.56
A2246: 2245 | B2246: CA-2018-103380 | C2246: 43425 | D2246: 43429 | E2246: Standard Class | F2246: BF-11005 | G2246: Barry Franz | H2246: Home Office | I2246: United States | J2246: Pasadena | K2246: California | L2246: 91104 | M2246: West | N2246: OFF-FA-10004248 | O2246: Office Supplies | P2246: Fasteners | Q2246: Advantus T-Pin Paper Clips | R2246: 9.02
A2247: 2246 | B2247: CA-2018-103380 | C2247: 43425 | D2247: 43429 | E2247: Standard Class | F2247: BF-11005 | G2247: Barry Franz | H2247: Home Office | I2247: United States | J2247: Pasadena | K2247: California | L2247: 91104 | M2247: West | N2247: OFF-AP-10001492 | O2247: Office Supplies | P2247: Appliances | Q2247: Acco Six-Outlet Power Strip, 4' Cord Length | R2247: 8.62
A2248: 2247 | B2248: CA-2018-103380 | C2248: 43425 | D2248: 43429 | E2248: Standard Class | F2248: BF-11005 | G2248: Barry Franz | H2248: Home Office | I2248: United States | J2248: Pasadena | K2248: California | L2248: 91104 | M2248: West | N2248: TEC-PH-10004165 | O2248: Technology | P2248: Phones | Q2248: Mitel MiVoice 5330e IP Phone | R2248: 659.976
... A5275: 5274 | B5275: US-2017-158309 | C5275: 43065 | D5275: 43068 | E5275: First Class | F5275: PA-19060 | G5275: Pete Armstrong | H5275: Home Office | I5275: United States | J5275: Miami | K5275: Florida | L5275: 33142 | M5275: South | N5275: OFF-BI-10000145 | O5275: Office Supplies | P5275: Binders | Q5275: Zipper Ring Binder Pockets | R5275: 3.744
A5276: 5275 | B5276: CA-2016-162887 | C5276: 42681 | D5276: 42683 | E5276: Second Class | F5276: SV-20785 | G5276: Stewart Visinsky | H5276: Consumer | I5276: United States | J5276: Burlington | K5276: Vermont | M5276: East | N5276: FUR-CH-10000595 | O5276: Furniture | P5276: Chairs | Q5276: Safco Contoured Stacking Chairs | R5276: 715.2
A5277: 5276 | B5277: CA-2018-147333 | C5277: 43448 | D5277: 43454 | E5277: Standard Class | F5277: KL-16555 | G5277: Kelly Lampkin | H5277: Corporate | I5277: United States | J5277: Fayetteville | K5277: Arkansas | L5277: 72701 | M5277: South | N5277: TEC-AC-10004469 | O5277: Technology | P5277: Accessories | Q5277: Microsoft Sculpt Comfort Mouse | R5277: 159.8
A5278: 5277 | B5278: CA-2018-147333 | C5278: 43448 | D5278: 43454 | E5278: Standard Class | F5278: KL-16555 | G5278: Kelly Lampkin | H5278: Corporate | I5278: United States | J5278: Fayetteville | K5278: Arkansas | L5278: 72701 | M5278: South | N5278: TEC-AC-10003038 | O5278: Technology | P5278: Accessories | Q5278: Kingston Digital DataTraveler 16GB USB 2.0 | R5278: 44.75
A5279: 5278 | B5279: CA-2015-113859 | C5279: 42260 | D5279: 42264 | E5279: Standard Class | F5279: BC-11125 | G5279: Becky Castell | H5279: Home Office | I5279: United States | J5279: Odessa | K5279: Texas | L5279: 79762 | M5279: Central | N5279: FUR-CH-10004698 | O5279: Furniture | P5279: Chairs | Q5279: Padded Folding Chairs, Black, 4/Carton | R5279: 340.116
A5280: 5279 | B5280: CA-2015-159681 | C5280: 42345 | D5280: 42351 | E5280: Standard Class | F5280: PO-18850 | G5280: Patrick O'Brill | H5280: Consumer | I5280: United States | J5280: Virginia Beach | K5280: Virginia | L5280: 23464 | M5280: South | N5280: OFF-PA-10003641 | O5280: Office Supplies | P5280: Paper | Q5280: Xerox 1909 | R5280: 105.52
A5281: 5280 | B5281: US-2018-104094 | C5281: 43350 | D5281: 43354 | E5281: Standard Class | F5281: AG-10675 | G5281: Anna Gayman | H5281: Consumer | I5281: United States | J5281: Milwaukee | K5281: Wisconsin | L5281: 53209 | M5281: Central | N5281: TEC-AC-10002134 | O5281: Technology | P5281: Accessories | Q5281: Rosewill 107 Normal Keys USB Wired Standard Keyboard | R5281: 13.48
A5282: 5281 | B5282: CA-2018-152709 | C5282: 43380 | D5282: 43385 | E5282: Standard Class | F5282: DB-13210 | G5282: Dean Braden | H5282: Consumer | I5282: United States | J5282: Detroit | K5282: Michigan | L5282: 48234 | M5282: Central | N5282: OFF-ST-10001837 | O5282: Office Supplies | P5282: Storage | Q5282: SAFCO Mobile Desk Side File, Wire Frame | R5282: 85.52
A5283: 5282 | B5283: CA-2016-105158 | C5283: 42618 | D5283: 42623 | E5283: Standard Class | F5283: SP-20860 | G5283: Sung Pak | H5283: Corporate | I5283: United States | J5283: Rochester | K5283: Minnesota | L5283: 55901 | M5283: Central | N5283: FUR-FU-10001706 | O5283: Furniture | P5283: Furnishings | Q5283: Longer-Life Soft White Bulbs | R5283: 6.16
A5284: 5283 | B5284: CA-2016-105158 | C5284: 42618 | D5284: 42623 | E5284: Standard Class | F5284: SP-20860 | G5284: Sung Pak | H5284: Corporate | I5284: United States | J5284: Rochester | K5284: Minnesota | L5284: 55901 | M5284: Central | N5284: OFF-PA-10001970 | O5284: Office Supplies | P5284: Paper | Q5284: Xerox 1881 | R5284: 36.84
A5285: 5284 | B5285: CA-2015-133424 | C5285: 42093 | D5285: 42098 | E5285: Standard Class | F5285: Dl-13600 | G5285: Dorris liebe | H5285: Corporate | I5285: United States | J5285: Seattle | K5285: Washington | L5285: 98105 | M5285: West | N5285: OFF-ST-10002957 | O5285: Office Supplies | P5285: Storage | Q5285: Sterilite Show Offs Storage Containers | R5285: 15.84
A5286: 5285 | B5286: CA-2015-133424 | C5286: 42093 | D5286: 42098 | E5286: Standard Class | F5286: Dl-13600 | G5286: Dorris liebe | H5286: Corporate | I5286: United States | J5286: Seattle | K5286: Washington | L5286: 98105 | M5286: West | N5286: OFF-LA-10002312 | O5286: Office Supplies | P5286: Labels | Q5286: Avery 490 | R5286: 44.4
A5287: 5286 | B5287: CA-2018-105991 | C5287: 43225 | D5287: 43226 | E5287: First Class | F5287: LH-17020 | G5287: Lisa Hazard | H5287: Consumer | I5287: United States | J5287: Louisville | K5287: Colorado | L5287: 80027 | M5287: West | N5287: OFF-EN-10002600 | O5287: Office Supplies | P5287: Envelopes | Q5287: Redi-Strip #10 Envelopes, 4 1/8 x 9 1/2 | R5287: 21.24
A5288: 5287 | B5288: CA-2018-105991 | C5288: 43225 | D5288: 43226 | E5288: First Class | F5288: LH-17020 | G5288: Lisa Hazard | H5288: Consumer | I5288: United States | J5288: Louisville | K5288: Colorado | L5288: 80027 | M5288: West | N5288: OFF-BI-10003274 | O5288: Office Supplies | P5288: Binders | Q5288: Avery Durable Slant Ring Binders, No Labels | R5288: 9.552
... A8799: 8798 | B8799: CA-2017-106397 | C8799: 42923 | D8799: 42929 | E8799: Standard Class | F8799: MJ-17740 | G8799: Max Jones | H8799: Consumer | I8799: United States | J8799: Orem | K8799: Utah | L8799: 84057 | M8799: West | N8799: OFF-AR-10004602 | O8799: Office Supplies | P8799: Art | Q8799: Boston KS Multi-Size Manual Pencil Sharpener | R8799: 45.98
A8800: 8799 | B8800: US-2017-150140 | C8800: 42831 | D8800: 42835 | E8800: Standard Class | F8800: VM-21685 | G8800: Valerie Mitchum | H8800: Home Office | I8800: United States | J8800: Burlington | K8800: Vermont | M8800: East | N8800: TEC-PH-10002555 | O8800: Technology | P8800: Phones | Q8800: Nortel Meridian M5316 Digital phone | R8800: 1294.75
A8801: 8800 | B8801: CA-2015-116666 | C8801: 42132 | D8801: 42134 | E8801: First Class | F8801: KT-16480 | G8801: Kean Thornton | H8801: Consumer | I8801: United States | J8801: Philadelphia | K8801: Pennsylvania | L8801: 19134 | M8801: East | N8801: TEC-CO-10001449 | O8801: Technology | P8801: Copiers | Q8801: Hewlett Packard LaserJet 3310 Copier | R8801: 1799.97
A8802: 8801 | B8802: CA-2018-148992 | C8802: 43427 | D8802: 43431 | E8802: Standard Class | F8802: CS-12250 | G8802: Chris Selesnick | H8802: Corporate | I8802: United States | J8802: Chicago | K8802: Illinois | L8802: 60623 | M8802: Central | N8802: OFF-PA-10004285 | O8802: Office Supplies | P8802: Paper | Q8802: Xerox 1959 | R8802: 10.688
A8803: 8802 | B8803: CA-2017-140935 | C8803: 43049 | D8803: 43051 | E8803: First Class | F8803: AB-10015 | G8803: Aaron Bergman | H8803: Consumer | I8803: United States | J8803: Oklahoma City | K8803: Oklahoma | L8803: 73120 | M8803: Central | N8803: TEC-PH-10000562 | O8803: Technology | P8803: Phones | Q8803: Samsung Convoy 3 | R8803: 221.98
A8804: 8803 | B8804: CA-2017-140935 | C8804: 43049 | D8804: 43051 | E8804: First Class | F8804: AB-10015 | G8804: Aaron Bergman | H8804: Consumer | I8804: United States | J8804: Oklahoma City | K8804: Oklahoma | L8804: 73120 | M8804: Central | N8804: FUR-BO-10003966 | O8804: Furniture | P8804: Bookcases | Q8804: Sauder Facets Collection Library, Sky Alder Finish | R8804: 341.96
A8805: 8804 | B8805: CA-2015-157644 | C8805: 42369 | D8805: 42370 | E8805: First Class | F8805: AH-10030 | G8805: Aaron Hawkins | H8805: Corporate | I8805: United States | J8805: New York City | K8805: New York | L8805: 10035 | M8805: East | N8805: TEC-AC-10003614 | O8805: Technology | P8805: Accessories | Q8805: Verbatim 25 GB 6x Blu-ray Single Layer Recordable Disc, 10/Pack | R8805: 34.77
A8806: 8805 | B8806: CA-2015-157644 | C8806: 42369 | D8806: 42370 | E8806: First Class | F8806: AH-10030 | G8806: Aaron Hawkins | H8806: Corporate | I8806: United States | J8806: New York City | K8806: New York | L8806: 10035 | M8806: East | N8806: OFF-LA-10003148 | O8806: Office Supplies | P8806: Labels | Q8806: Avery 51 | R8806: 18.9
A8807: 8806 | B8807: US-2018-100398 | C8807: 43331 | D8807: 43335 | E8807: Standard Class | F8807: DO-13435 | G8807: Denny Ordway | H8807: Consumer | I8807: United States | J8807: Salt Lake City | K8807: Utah | L8807: 84106 | M8807: West | N8807: OFF-BI-10002133 | O8807: Office Supplies | P8807: Binders | Q8807: Wilson Jones Elliptical Ring 3 1/2" Capacity Binders, 800 sheets | R8807: 102.72
A8808: 8807 | B8808: CA-2017-113082 | C8808: 42990 | D8808: 42994 | E8808: Standard Class | F8808: MC-17590 | G8808: Matt Collister | H8808: Corporate | I8808: United States | J8808: Utica | K8808: New York | L8808: 13501 | M8808: East | N8808: FUR-FU-10002813 | O8808: Furniture | P8808: Furnishings | Q8808: DAX Contemporary Wood Frame with Silver Metal Mat, Desktop, 11 x 14 Size | R8808: 40.48
A8809: 8808 | B8809: US-2018-110646 | C8809: 43399 | D8809: 43404 | E8809: Standard Class | F8809: JF-15190 | G8809: Jamie Frazer | H8809: Consumer | I8809: United States | J8809: Philadelphia | K8809: Pennsylvania | L8809: 19134 | M8809: East | N8809: OFF-BI-10004330 | O8809: Office Supplies | P8809: Binders | Q8809: GBC Velobind Prepunched Cover Sets, Regency Series | R8809: 33.282
A8810: 8809 | B8810: US-2018-110646 | C8810: 43399 | D8810: 43404 | E8810: Standard Class | F8810: JF-15190 | G8810: Jamie Frazer | H8810: Consumer | I8810: United States | J8810: Philadelphia | K8810: Pennsylvania | L8810: 19134 | M8810: East | N8810: TEC-PH-10002807 | O8810: Technology | P8810: Phones | Q8810: Motorla HX550 Universal Bluetooth Headset | R8810: 118.65
A8811: 8810 | B8811: US-2018-110646 | C8811: 43399 | D8811: 43404 | E8811: Standard Class | F8811: JF-15190 | G8811: Jamie Frazer | H8811: Consumer | I8811: United States | J8811: Philadelphia | K8811: Pennsylvania | L8811: 19134 | M8811: East | N8811: OFF-LA-10001404 | O8811: Office Supplies | P8811: Labels | Q8811: Avery 517 | R8811: 14.76
A8812: 8811 | B8812: CA-2018-120614 | C8812: 43250 | D8812: 43255 | E8812: Standard Class | F8812: SM-20950 | G8812: Suzanne McNair | H8812: Corporate | I8812: United States | J8812: Los Angeles | K8812: California | L8812: 90004 | M8812: West | N8812: OFF-PA-10004911 | O8812: Office Supplies | P8812: Paper | Q8812: Rediform S.O.S. 1-Up Phone Message Bk, 4-1/4x3-1/16 Bk, 1 Form/Pg, 40 Messages/Bk, 3/Pk | R8812: 37.52
... A9147: 9146 | B9147: CA-2016-126970 | C9147: 42633 | D9147: 42637 | E9147: Standard Class | F9147: TP-21130 | G9147: Theone Pippenger | H9147: Consumer | I9147: United States | J9147: Naperville | K9147: Illinois | L9147: 60540 | M9147: Central | N9147: OFF-BI-10000138 | O9147: Office Supplies | P9147: Binders | Q9147: Acco Translucent Poly Ring Binders | R9147: 2.808
A9148: 9147 | B9148: US-2017-165505 | C9148: 42758 | D9148: 42762 | E9148: Standard Class | F9148: CB-12535 | G9148: Claudia Bergmann | H9148: Corporate | I9148: United States | J9148: Burlington | K9148: Vermont | M9148: East | N9148: TEC-AC-10002926 | O9148: Technology | P9148: Accessories | Q9148: Logitech Wireless Marathon Mouse M705 | R9148: 99.98
A9149: 9148 | B9149: US-2017-165505 | C9149: 42758 | D9149: 42762 | E9149: Standard Class | F9149: CB-12535 | G9149: Claudia Bergmann | H9149: Corporate | I9149: United States | J9149: Burlington | K9149: Vermont | M9149: East | N9149: OFF-AR-10003477 | O9149: Office Supplies | P9149: Art | Q9149: 4009 Highlighters | R9149: 8.04
A9150: 9149 | B9150: US-2017-165505 | C9150: 42758 | D9150: 42762 | E9150: Standard Class | F9150: CB-12535 | G9150: Claudia Bergmann | H9150: Corporate | I9150: United States | J9150: Burlington | K9150: Vermont | M9150: East | N9150: OFF-ST-10001526 | O9150: Office Supplies | P9150: Storage | Q9150: Iceberg Mobile Mega Data/Printer Cart | R9150: 1564.29
A9151: 9150 | B9151: US-2015-157070 | C9151: 42156 | D9151: 42161 | E9151: Standard Class | F9151: QJ-19255 | G9151: Quincy Jones | H9151: Corporate | I9151: United States | J9151: Detroit | K9151: Michigan | L9151: 48234 | M9151: Central | N9151: OFF-BI-10001765 | O9151: Office Supplies | P9151: Binders | Q9151: Wilson Jones Heavy-Duty Casebound Ring Binders with Metal Hinges | R9151: 138.56
A9152: 9151 | B9152: US-2015-157070 | C9152: 42156 | D9152: 42161 | E9152: Standard Class | F9152: QJ-19255 | G9152: Quincy Jones | H9152: Corporate | I9152: United States | J9152: Detroit | K9152: Michigan | L9152: 48234 | M9152: Central | N9152: OFF-AP-10004859 | O9152: Office Supplies | P9152: Appliances | Q9152: Acco 6 Outlet Guardian Premium Surge Suppressor | R9152: 65.52
A9153: 9152 | B9153: US-2016-106873 | C9153: 42637 | D9153: 42642 | E9153: Second Class | F9153: KM-16720 | G9153: Kunst Miller | H9153: Consumer | I9153: United States | J9153: Avondale | K9153: Arizona | L9153: 85323 | M9153: West | N9153: OFF-AR-10003179 | O9153: Office Supplies | P9153: Art | Q9153: Dixon Ticonderoga Core-Lock Colored Pencils | R9153: 14.576
A9154: 9153 | B9154: US-2016-106873 | C9154: 42637 | D9154: 42642 | E9154: Second Class | F9154: KM-16720 | G9154: Kunst Miller | H9154: Consumer | I9154: United States | J9154: Avondale | K9154: Arizona | L9154: 85323 | M9154: West | N9154: TEC-AC-10002345 | O9154: Technology | P9154: Accessories | Q9154: HP Standard 104 key PS/2 Keyboard | R9154: 23.2
A9155: 9154 | B9155: US-2016-106873 | C9155: 42637 | D9155: 42642 | E9155: Second Class | F9155: KM-16720 | G9155: Kunst Miller | H9155: Consumer | I9155: United States | J9155: Avondale | K9155: Arizona | L9155: 85323 | M9155: West | N9155: OFF-AR-10001246 | O9155: Office Supplies | P9155: Art | Q9155: Newell 317 | R9155: 16.464
A9156: 9155 | B9156: CA-2017-132990 | C9156: 42948 | D9156: 42950 | E9156: Second Class | F9156: KM-16660 | G9156: Khloe Miller | H9156: Consumer | I9156: United States | J9156: Philadelphia | K9156: Pennsylvania | L9156: 19140 | M9156: East | N9156: FUR-FU-10004864 | O9156: Furniture | P9156: Furnishings | Q9156: Eldon 500 Class Desk Accessories | R9156: 19.312
A9157: 9156 | B9157: CA-2015-102645 | C9157: 42027 | D9157: 42032 | E9157: Standard Class | F9157: IM-15055 | G9157: Ionia McGrath | H9157: Consumer | I9157: United States | J9157: Las Vegas | K9157: Nevada | L9157: 89115 | M9157: West | N9157: OFF-PA-10001804 | O9157: Office Supplies | P9157: Paper | Q9157: Xerox 195 | R9157: 40.08
A9158: 9157 | B9158: CA-2015-134215 | C9158: 42220 | D9158: 42224 | E9158: Standard Class | F9158: ML-17395 | G9158: Marina Lichtenstein | H9158: Corporate | I9158: United States | J9158: Bangor | K9158: Maine | L9158: 4401 | M9158: East | N9158: OFF-AP-10001271 | O9158: Office Supplies | P9158: Appliances | Q9158: Eureka The Boss Cordless Rechargeable Stick Vac | R9158: 101.96
A9159: 9158 | B9159: CA-2015-134215 | C9159: 42220 | D9159: 42224 | E9159: Standard Class | F9159: ML-17395 | G9159: Marina Lichtenstein | H9159: Corporate | I9159: United States | J9159: Bangor | K9159: Maine | L9159: 4401 | M9159: East | N9159: OFF-PA-10004353 | O9159: Office Supplies | P9159: Paper | Q9159: Southworth 25% Cotton Premium Laser Paper and Envelopes | R9159: 259.74
A9160: 9159 | B9160: CA-2015-134215 | C9160: 42220 | D9160: 42224 | E9160: Standard Class | F9160: ML-17395 | G9160: Marina Lichtenstein | H9160: Corporate | I9160: United States | J9160: Bangor | K9160: Maine | L9160: 4401 | M9160: East | N9160: TEC-AC-10002473 | O9160: Technology | P9160: Accessories | Q9160: Maxell 4.7GB DVD-R | R9160: 255.42
A9161: 9160 | B9161: CA-2017-118934 | C9161: 42956 | D9161: 42961 | E9161: Standard Class | F9161: GH-14410 | G9161: Gary Hansen | H9161: Home Office | I9161: United States | J9161: Hendersonville | K9161: Tennessee | L9161: 37075 | M9161: South | N9161: OFF-BI-10003314 | O9161: Office Supplies | P9161: Binders | Q9161: Tuff Stuff Recycled Round Ring Binders | R9161: 4.338
A9162: 9161 | B9162: CA-2017-118934 | C9162: 42956 | D9162: 42961 | E9162: Standard Class | F9162: GH-14410 | G9162: Gary Hansen | H9162: Home Office | I9162: United States | J9162: Hendersonville | K9162: Tennessee | L9162: 37075 | M9162: South | N9162: OFF-BI-10004465 | O9162: Office Supplies | P9162: Binders | Q9162: Avery Durable Slant Ring Binders | R9162: 11.88
... A9387: 9386 | B9387: CA-2018-163097 | C9387: 43339 | D9387: 43343 | E9387: Standard Class | F9387: SF-20200 | G9387: Sarah Foster | H9387: Consumer | I9387: United States | J9387: Mesa | K9387: Arizona | L9387: 85204 | M9387: West | N9387: FUR-FU-10004973 | O9387: Furniture | P9387: Furnishings | Q9387: Flat Face Poster Frame | R9387: 120.576
A9388: 9387 | B9388: US-2018-127292 | C9388: 43119 | D9388: 43123 | E9388: Standard Class | F9388: RM-19375 | G9388: Raymond Messe | H9388: Consumer | I9388: United States | J9388: Burlington | K9388: Vermont | M9388: East | N9388: OFF-PA-10000157 | O9388: Office Supplies | P9388: Paper | Q9388: Xerox 191 | R9388: 79.92
A9389: 9388 | B9389: US-2018-127292 | C9389: 43119 | D9389: 43123 | E9389: Standard Class | F9389: RM-19375 | G9389: Raymond Messe | H9389: Consumer | I9389: United States | J9389: Burlington | K9389: Vermont | M9389: East | N9389: OFF-PA-10001970 | O9389: Office Supplies | P9389: Paper | Q9389: Xerox 1881 | R9389: 12.28
A9390: 9389 | B9390: US-2018-127292 | C9390: 43119 | D9390: 43123 | E9390: Standard Class | F9390: RM-19375 | G9390: Raymond Messe | H9390: Consumer | I9390: United States | J9390: Burlington | K9390: Vermont | M9390: East | N9390: OFF-AP-10000828 | O9390: Office Supplies | P9390: Appliances | Q9390: Avanti 4.4 Cu. Ft. Refrigerator | R9390: 542.94
A9391: 9390 | B9391: US-2018-127292 | C9391: 43119 | D9391: 43123 | E9391: Standard Class | F9391: RM-19375 | G9391: Raymond Messe | H9391: Consumer | I9391: United States | J9391: Burlington | K9391: Vermont | M9391: East | N9391: OFF-EN-10001509 | O9391: Office Supplies | P9391: Envelopes | Q9391: Poly String Tie Envelopes | R9391: 2.04
A9392: 9391 | B9392: CA-2016-163734 | C9392: 42540 | D9392: 42545 | E9392: Standard Class | F9392: KM-16375 | G9392: Katherine Murray | H9392: Home Office | I9392: United States | J9392: Houston | K9392: Texas | L9392: 77070 | M9392: Central | N9392: OFF-ST-10003692 | O9392: Office Supplies | P9392: Storage | Q9392: Recycled Steel Personal File for Hanging File Folders | R9392: 228.92
A9393: 9392 | B9393: CA-2018-162474 | C9393: 43172 | D9393: 43175 | E9393: First Class | F9393: FH-14275 | G9393: Frank Hawley | H9393: Corporate | I9393: United States | J9393: Aurora | K9393: Illinois | L9393: 60505 | M9393: Central | N9393: TEC-PH-10004700 | O9393: Technology | P9393: Phones | Q9393: PowerGen Dual USB Car Charger | R9393: 7.992
A9394: 9393 | B9394: CA-2016-130848 | C9394: 42668 | D9394: 42668 | E9394: Same Day | F9394: DG-13300 | G9394: Deirdre Greer | H9394: Corporate | I9394: United States | J9394: Denver | K9394: Colorado | L9394: 80219 | M9394: West | N9394: FUR-CH-10000422 | O9394: Furniture | P9394: Chairs | Q9394: Global Highback Leather Tilter in Burgundy | R9394: 582.336
A9395: 9394 | B9395: CA-2015-125997 | C9395: 42267 | D9395: 42270 | E9395: First Class | F9395: MW-18220 | G9395: Mitch Webber | H9395: Consumer | I9395: United States | J9395: New York City | K9395: New York | L9395: 10011 | M9395: East | N9395: TEC-PH-10003484 | O9395: Technology | P9395: Phones | Q9395: Ooma Telo VoIP Home Phone System | R9395: 629.95
A9396: 9395 | B9396: CA-2015-125997 | C9396: 42267 | D9396: 42270 | E9396: First Class | F9396: MW-18220 | G9396: Mitch Webber | H9396: Consumer | I9396: United States | J9396: New York City | K9396: New York | L9396: 10011 | M9396: East | N9396: FUR-CH-10001394 | O9396: Furniture | P9396: Chairs | Q9396: Global Leather Executive Chair | R9396: 631.782
A9397: 9396 | B9397: CA-2015-125997 | C9397: 42267 | D9397: 42270 | E9397: First Class | F9397: MW-18220 | G9397: Mitch Webber | H9397: Consumer | I9397: United States | J9397: New York City | K9397: New York | L9397: 10011 | M9397: East | N9397: FUR-BO-10002213 | O9397: Furniture | P9397: Bookcases | Q9397: DMI Eclipse Executive Suite Bookcases | R9397: 801.568
A9398: 9397 | B9398: CA-2015-125997 | C9398: 42267 | D9398: 42270 | E9398: First Class | F9398: MW-18220 | G9398: Mitch Webber | H9398: Consumer | I9398: United States | J9398: New York City | K9398: New York | L9398: 10011 | M9398: East | N9398: OFF-LA-10002762 | O9398: Office Supplies | P9398: Labels | Q9398: Avery 485 | R9398: 75.18
A9399: 9398 | B9399: CA-2015-125997 | C9399: 42267 | D9399: 42270 | E9399: First Class | F9399: MW-18220 | G9399: Mitch Webber | H9399: Consumer | I9399: United States | J9399: New York City | K9399: New York | L9399: 10011 | M9399: East | N9399: OFF-AP-10003842 | O9399: Office Supplies | P9399: Appliances | Q9399: Euro-Pro Shark Turbo Vacuum | R9399: 30.98
A9400: 9399 | B9400: CA-2015-125997 | C9400: 42267 | D9400: 42270 | E9400: First Class | F9400: MW-18220 | G9400: Mitch Webber | H9400: Consumer | I9400: United States | J9400: New York City | K9400: New York | L9400: 10011 | M9400: East | N9400: TEC-PH-10003072 | O9400: Technology | P9400: Phones | Q9400: Panasonic KX-TG9541B DECT 6.0 Digital 2-Line Expandable Cordless Phone With Digital Answering System | R9400: 1349.91
A9401: 9400 | B9401: CA-2017-103128 | C9401: 43050 | D9401: 43054 | E9401: Standard Class | F9401: SC-20845 | G9401: Sung Chung | H9401: Consumer | I9401: United States | J9401: Arlington Heights | K9401: Illinois | L9401: 60004 | M9401: Central | N9401: OFF-AR-10003394 | O9401: Office Supplies | P9401: Art | Q9401: Newell 332 | R9401: 14.112
A9402: 9401 | B9402: CA-2016-167696 | C9402: 42629 | D9402: 42634 | E9402: Standard Class | F9402: BD-11500 | G9402: Bradley Drucker | H9402: Consumer | I9402: United States | J9402: Newport News | K9402: Virginia | L9402: 23602 | M9402: South | N9402: OFF-EN-10001539 | O9402: Office Supplies | P9402: Envelopes | Q9402: Staple envelope | R9402: 31.12
A9403: 9402 | B9403: CA-2015-159814 | C9403: 42179 | D9403: 42183 | E9403: Standard Class | F9403: LP-17080 | G9403: Liz Pelletier | H9403: Consumer | I9403: United States | J9403: Tucson | K9403: Arizona | L9403: 85705 | M9403: West | N9403: FUR-FU-10001731 | O9403: Furniture | P9403: Furnishings | Q9403: Acrylic Self-Standing Desk Frames | R9403: 4.272
... A9742: 9741 | B9742: CA-2018-129294 | C9742: 43175 | D9742: 43180 | E9742: Standard Class | F9742: KD-16615 | G9742: Ken Dana | H9742: Corporate | I9742: United States | J9742: Los Angeles | K9742: California | L9742: 90032 | M9742: West | N9742: OFF-AP-10001154 | O9742: Office Supplies | P9742: Appliances | Q9742: Bionaire Personal Warm Mist Humidifier/Vaporizer | R9742: 140.67
A9743: 9742 | B9743: CA-2016-117086 | C9743: 42682 | D9743: 42686 | E9743: Standard Class | F9743: QJ-19255 | G9743: Quincy Jones | H9743: Corporate | I9743: United States | J9743: Burlington | K9743: Vermont | M9743: East | N9743: FUR-BO-10004834 | O9743: Furniture | P9743: Bookcases | Q9743: Riverside Palais Royal Lawyers Bookcase, Royale Cherry Finish | R9743: 4404.9
A9744: 9743 | B9744: CA-2018-131303 | C9744: 43432 | D9744: 43436 | E9744: Standard Class | F9744: EP-13915 | G9744: Emily Phan | H9744: Consumer | I9744: United States | J9744: San Diego | K9744: California | L9744: 92037 | M9744: West | N9744: OFF-LA-10001074 | O9744: Office Supplies | P9744: Labels | Q9744: Round Specialty Laser Printer Labels | R9744: 62.65
A9745: 9744 | B9745: CA-2017-137127 | C9745: 42902 | D9745: 42908 | E9745: Standard Class | F9745: JJ-15445 | G9745: Jennifer Jackson | H9745: Consumer | I9745: United States | J9745: Newark | K9745: Delaware | L9745: 19711 | M9745: East | N9745: OFF-LA-10001641 | O9745: Office Supplies | P9745: Labels | Q9745: Avery 518 | R9745: 9.45
A9746: 9745 | B9746: CA-2018-141782 | C9746: 43121 | D9746: 43125 | E9746: Standard Class | F9746: BE-11410 | G9746: Bobby Elias | H9746: Consumer | I9746: United States | J9746: Aurora | K9746: Illinois | L9746: 60505 | M9746: Central | N9746: OFF-EN-10002230 | O9746: Office Supplies | P9746: Envelopes | Q9746: Airmail Envelopes | R9746: 268.576
A9747: 9746 | B9747: CA-2018-137505 | C9747: 43428 | D9747: 43428 | E9747: Same Day | F9747: BP-11290 | G9747: Beth Paige | H9747: Consumer | I9747: United States | J9747: Los Angeles | K9747: California | L9747: 90008 | M9747: West | N9747: FUR-TA-10000617 | O9747: Furniture | P9747: Tables | Q9747: Hon Practical Foundations 30 x 60 Training Table, Light Gray/Charcoal | R9747: 364.08
A9748: 9747 | B9748: CA-2018-137505 | C9748: 43428 | D9748: 43428 | E9748: Same Day | F9748: BP-11290 | G9748: Beth Paige | H9748: Consumer | I9748: United States | J9748: Los Angeles | K9748: California | L9748: 90008 | M9748: West | N9748: FUR-TA-10001676 | O9748: Furniture | P9748: Tables | Q9748: Hon 61000 Series Interactive Training Tables | R9748: 71.088
A9749: 9748 | B9749: US-2015-140914 | C9749: 42319 | D9749: 42323 | E9749: Standard Class | F9749: BH-11710 | G9749: Brosina Hoffman | H9749: Consumer | I9749: United States | J9749: Chicago | K9749: Illinois | L9749: 60653 | M9749: Central | N9749: FUR-FU-10000175 | O9749: Furniture | P9749: Furnishings | Q9749: DAX Wood Document Frame. | R9749: 10.984
A9750: 9749 | B9750: US-2015-140914 | C9750: 42319 | D9750: 42323 | E9750: Standard Class | F9750: BH-11710 | G9750: Brosina Hoffman | H9750: Consumer | I9750: United States | J9750: Chicago | K9750: Illinois | L9750: 60653 | M9750: Central | N9750: FUR-CH-10003379 | O9750: Furniture | P9750: Chairs | Q9750: Global Commerce Series High-Back Swivel/Tilt Chairs | R9750: 797.944
A9751: 9750 | B9751: CA-2017-158358 | C9751: 42798 | D9751: 42802 | E9751: Standard Class | F9751: EM-13810 | G9751: Eleni McCrary | H9751: Corporate | I9751: United States | J9751: Dover | K9751: New Hampshire | L9751: 3820 | M9751: East | N9751: TEC-AC-10002567 | O9751: Technology | P9751: Accessories | Q9751: Logitech G602 Wireless Gaming Mouse | R9751: 159.98
A9752: 9751 | B9752: CA-2017-113390 | C9752: 43019 | D9752: 43023 | E9752: Standard Class | F9752: EP-13915 | G9752: Emily Phan | H9752: Consumer | I9752: United States | J9752: Chicago | K9752: Illinois | L9752: 60610 | M9752: Central | N9752: OFF-AR-10003183 | O9752: Office Supplies | P9752: Art | Q9752: Avery Fluorescent Highlighter Four-Color Set | R9752: 5.344
A9753: 9752 | B9753: CA-2017-113390 | C9753: 43019 | D9753: 43023 | E9753: Standard Class | F9753: EP-13915 | G9753: Emily Phan | H9753: Consumer | I9753: United States | J9753: Chicago | K9753: Illinois | L9753: 60610 | M9753: Central | N9753: OFF-AR-10001446 | O9753: Office Supplies | P9753: Art | Q9753: Newell 309 | R9753: 27.72
...
